[
  {
    "full_name": "mairod/screensaver-js",
    "stargazers_count": 42,
    "open_issues_count": 1,
    "forks_count": 7
  },
  {
    "full_name": "Kirilllive/tuesday-js",
    "stargazers_count": 141,
    "open_issues_count": 0,
    "forks_count": 23
  },
  {
    "full_name": "ShizukuIchi/pdf-editor",
    "stargazers_count": 742,
    "open_issues_count": 27,
    "forks_count": 152
  },
  {
    "full_name": "nypublicradio/audiogram",
    "stargazers_count": 870,
    "open_issues_count": 46,
    "forks_count": 322
  },
  {
    "full_name": "webslides/WebSlides",
    "stargazers_count": 5872,
    "open_issues_count": 68,
    "forks_count": 577
  },
  {
    "full_name": "danielireson/formplug",
    "stargazers_count": 249,
    "open_issues_count": 7,
    "forks_count": 28
  },
  {
    "full_name": "kormyen/memex",
    "stargazers_count": 413,
    "open_issues_count": 3,
    "forks_count": 60
  },
  {
    "full_name": "billydh/zoom-reporting",
    "stargazers_count": 17,
    "open_issues_count": 2,
    "forks_count": 12
  },
  {
    "full_name": "bradleytaunt/wyf",
    "stargazers_count": 5,
    "open_issues_count": 0,
    "forks_count": 0
  },
  {
    "full_name": "nprapps/pym.js",
    "stargazers_count": 794,
    "open_issues_count": 1,
    "forks_count": 116
  },
  {
    "full_name": "McFunkypants/CYOAwesome",
    "stargazers_count": 22,
    "open_issues_count": 0,
    "forks_count": 8
  },
  {
    "full_name": "michaelbourne/gravity-forms-zoom-webinar-registration",
    "stargazers_count": 19,
    "open_issues_count": 6,
    "forks_count": 12
  },
  {
    "full_name": "harvard-dce/zoom-recording-ingester",
    "stargazers_count": 19,
    "open_issues_count": 8,
    "forks_count": 5
  },
  {
    "full_name": "nprapps/interactive-template",
    "stargazers_count": 44,
    "open_issues_count": 2,
    "forks_count": 15
  },
  {
    "full_name": "nprapps/lunchbox",
    "stargazers_count": 162,
    "open_issues_count": 23,
    "forks_count": 149
  },
  {
    "full_name": "nprapps/book-concierge",
    "stargazers_count": 26,
    "open_issues_count": 13,
    "forks_count": 8
  },
  {
    "full_name": "microsoft/PowerPlatformConnectors",
    "stargazers_count": 502,
    "open_issues_count": 46,
    "forks_count": 739
  },
  {
    "full_name": "storybookjs/storybook",
    "stargazers_count": 72715,
    "open_issues_count": 1903,
    "forks_count": 7506
  },
  {
    "full_name": "osano/cookieconsent",
    "stargazers_count": 3122,
    "open_issues_count": 82,
    "forks_count": 590
  },
  {
    "full_name": "adamwulf/app-launch-guide",
    "stargazers_count": 3883,
    "open_issues_count": 8,
    "forks_count": 233
  },
  {
    "full_name": "vapid/vapid",
    "stargazers_count": 1541,
    "open_issues_count": 17,
    "forks_count": 66
  },
  {
    "full_name": "nuket/google-sheets-geocoding-macro",
    "stargazers_count": 286,
    "open_issues_count": 1,
    "forks_count": 140
  },
  {
    "full_name": "MunGell/awesome-for-beginners",
    "stargazers_count": 41559,
    "open_issues_count": 93,
    "forks_count": 5691
  },
  {
    "full_name": "gatsbyjs/gatsby",
    "stargazers_count": 53202,
    "open_issues_count": 338,
    "forks_count": 10355
  },
  {
    "full_name": "11ty/eleventy",
    "stargazers_count": 12373,
    "open_issues_count": 421,
    "forks_count": 384
  },
  {
    "full_name": "postlight/headless-wp-starter",
    "stargazers_count": 4237,
    "open_issues_count": 58,
    "forks_count": 634
  },
  {
    "full_name": "carcin/google-script-ticketing-system",
    "stargazers_count": 18,
    "open_issues_count": 0,
    "forks_count": 8
  },
  {
    "full_name": "tarbell-project/tarbell",
    "stargazers_count": 161,
    "open_issues_count": 68,
    "forks_count": 33
  },
  {
    "full_name": "aaronpk/webmention.io",
    "stargazers_count": 570,
    "open_issues_count": 40,
    "forks_count": 34
  },
  {
    "full_name": "jlord/sheetsee.js",
    "stargazers_count": 2769,
    "open_issues_count": 69,
    "forks_count": 948
  }
]